{
    "jimdo-platform.net.": {
        "delegation": {
            "warnings": [
                {
                    "description": "Authoritative AAAA records exist for ns-737.awsdns-28.net, but there are no corresponding AAAA glue records.",
                    "code": "MISSING_GLUE_IPV6"
                }
            ]
        }
    },
    "jimdo.com.": {
        "delegation": {
            "warnings": [
                {
                    "description": "Authoritative AAAA records exist for ns-15.awsdns-01.com, but there are no corresponding AAAA glue records.",
                    "code": "MISSING_GLUE_IPV6"
                }
            ]
        }
    },
    "jimdofree.com.": {
        "delegation": {
            "warnings": [
                {
                    "description": "Authoritative AAAA records exist for ns-462.awsdns-57.com, but there are no corresponding AAAA glue records.",
                    "code": "MISSING_GLUE_IPV6"
                }
            ]
        }
    }
}