{
    "prabhatkhabar.com.": {
        "queries": {
            "prabhatkhabar.com./IN/A": {
                "answer": [
                    {
                        "id": "prabhatkhabar.com./IN/A",
                        "warnings": [
                            {
                                "description": "The response had an invalid RCODE (FORMERR) until EDNS was disabled.",
                                "code": "ERROR_WITH_EDNS",
                                "servers": [
                                    "103.115.194.104"
                                ],
                                "query_options": [
                                    "UDP_-_EDNS0_4096_D_K"
                                ]
                            }
                        ]
                    }
                ]
            },
            "prabhatkhabar.com./IN/NS": {
                "answer": [
                    {
                        "id": "prabhatkhabar.com./IN/NS",
                        "warnings": [
                            {
                                "description": "The response had an invalid RCODE (FORMERR) until EDNS was disabled.",
                                "code": "ERROR_WITH_EDNS",
                                "servers": [
                                    "103.115.194.104"
                                ],
                                "query_options": [
                                    "UDP_-_EDNS0_4096_D_K"
                                ]
                            }
                        ]
                    }
                ]
            },
            "prabhatkhabar.com./IN/CNAME": {
                "nodata": [
                    {
                        "id": "prabhatkhabar.com./IN/CNAME",
                        "warnings": [
                            {
                                "description": "The response had an invalid RCODE (FORMERR) until EDNS was disabled.",
                                "code": "ERROR_WITH_EDNS",
                                "servers": [
                                    "103.115.194.104"
                                ],
                                "query_options": [
                                    "UDP_-_EDNS0_4096_D_K"
                                ]
                            }
                        ]
                    }
                ]
            },
            "prabhatkhabar.com./IN/SOA": {
                "answer": [
                    {
                        "id": "prabhatkhabar.com./IN/SOA",
                        "warnings": [
                            {
                                "description": "The response had an invalid RCODE (FORMERR) until EDNS was disabled.",
                                "code": "ERROR_WITH_EDNS",
                                "servers": [
                                    "103.115.194.104"
                                ],
                                "query_options": [
                                    "UDP_-_EDNS0_4096_D_K",
                                    "UDP_-_EDNS0_4096_D_K_0x20"
                                ]
                            }
                        ]
                    }
                ]
            },
            "prabhatkhabar.com./IN/MX": {
                "answer": [
                    {
                        "id": "prabhatkhabar.com./IN/MX",
                        "warnings": [
                            {
                                "description": "The response had an invalid RCODE (FORMERR) until EDNS was disabled.",
                                "code": "ERROR_WITH_EDNS",
                                "servers": [
                                    "103.115.194.104"
                                ],
                                "query_options": [
                                    "UDP_-_EDNS0_4096_D_K"
                                ]
                            }
                        ]
                    }
                ],
                "error": [
                    {
                        "description": "The response had an invalid RCODE (FORMERR).",
                        "code": "INVALID_RCODE",
                        "servers": [
                            "103.115.194.104"
                        ],
                        "query_options": [
                            "UDP_-_EDNS0_512_D_K"
                        ]
                    }
                ]
            },
            "prabhatkhabar.com./IN/TXT": {
                "nodata": [
                    {
                        "id": "prabhatkhabar.com./IN/TXT",
                        "warnings": [
                            {
                                "description": "The response had an invalid RCODE (FORMERR) until EDNS was disabled.",
                                "code": "ERROR_WITH_EDNS",
                                "servers": [
                                    "103.115.194.104"
                                ],
                                "query_options": [
                                    "UDP_-_EDNS0_4096_D_K"
                                ]
                            }
                        ]
                    }
                ]
            },
            "prabhatkhabar.com./IN/AAAA": {
                "nodata": [
                    {
                        "id": "prabhatkhabar.com./IN/AAAA",
                        "warnings": [
                            {
                                "description": "The response had an invalid RCODE (FORMERR) until EDNS was disabled.",
                                "code": "ERROR_WITH_EDNS",
                                "servers": [
                                    "103.115.194.104"
                                ],
                                "query_options": [
                                    "UDP_-_EDNS0_4096_D_K"
                                ]
                            }
                        ]
                    }
                ]
            },
            "prabhatkhabar.com./IN/DNSKEY": {
                "nodata": [
                    {
                        "id": "prabhatkhabar.com./IN/DNSKEY",
                        "warnings": [
                            {
                                "description": "The response had an invalid RCODE (FORMERR) until EDNS was disabled.",
                                "code": "ERROR_WITH_EDNS",
                                "servers": [
                                    "103.115.194.104"
                                ],
                                "query_options": [
                                    "UDP_-_EDNS0_4096_D_K"
                                ]
                            }
                        ]
                    }
                ],
                "error": [
                    {
                        "description": "The response had an invalid RCODE (FORMERR).",
                        "code": "INVALID_RCODE",
                        "servers": [
                            "103.115.194.104"
                        ],
                        "query_options": [
                            "UDP_-_EDNS0_512_D_K"
                        ]
                    }
                ]
            },
            "mtb0vwpuxa.prabhatkhabar.com./IN/A": {
                "nxdomain": [
                    {
                        "id": "mtb0vwpuxa.prabhatkhabar.com./IN/A",
                        "warnings": [
                            {
                                "description": "The response had an invalid RCODE (FORMERR) until EDNS was disabled.",
                                "code": "ERROR_WITH_EDNS",
                                "servers": [
                                    "103.115.194.104"
                                ],
                                "query_options": [
                                    "UDP_-_EDNS0_4096_D_K"
                                ]
                            }
                        ]
                    }
                ]
            }
        },
        "delegation": {
            "warnings": [
                {
                    "description": "The following NS name(s) were found in the delegation NS RRset (i.e., in the com zone), but not in the authoritative NS RRset: ns4.4cplus.com",
                    "code": "NS_NAME_NOT_IN_CHILD"
                }
            ]
        }
    }
}