{
    ".": {
        "queries": {
            "./IN/DNSKEY": {
                "answer": [
                    {
                        "id": "./IN/DNSKEY",
                        "warnings": [
                            {
                                "description": "The server responded with no OPT record, rather than with RCODE FORMERR.",
                                "code": "EDNS_IGNORED",
                                "servers": [
                                    "223.5.5.5"
                                ],
                                "query_options": [
                                    "UDP_+_EDNS0_4096_D_K",
                                    "UDP_+_EDNS0_512_D_K"
                                ]
                            }
                        ],
                        "errors": [
                            {
                                "description": "No RRSIG covering the RRset was returned in the response.",
                                "code": "MISSING_RRSIG",
                                "servers": [
                                    "223.5.5.5"
                                ],
                                "query_options": [
                                    "UDP_+_EDNS0_4096_D_K",
                                    "UDP_+_EDNS0_512_D_K"
                                ]
                            }
                        ]
                    }
                ]
            }
        }
    },
    "top.": {
        "queries": {
            "top./IN/DS": {
                "answer": [
                    {
                        "id": "top./IN/DS",
                        "warnings": [
                            {
                                "description": "The server responded with no OPT record, rather than with RCODE FORMERR.",
                                "code": "EDNS_IGNORED",
                                "servers": [
                                    "223.5.5.5"
                                ],
                                "query_options": [
                                    "UDP_+_EDNS0_4096_D_K"
                                ]
                            }
                        ],
                        "errors": [
                            {
                                "description": "No RRSIG covering the RRset was returned in the response.",
                                "code": "MISSING_RRSIG",
                                "servers": [
                                    "223.5.5.5"
                                ],
                                "query_options": [
                                    "UDP_+_EDNS0_4096_D_K"
                                ]
                            }
                        ]
                    }
                ]
            },
            "top./IN/DNSKEY": {
                "answer": [
                    {
                        "id": "top./IN/DNSKEY",
                        "warnings": [
                            {
                                "description": "The server responded with no OPT record, rather than with RCODE FORMERR.",
                                "code": "EDNS_IGNORED",
                                "servers": [
                                    "223.5.5.5"
                                ],
                                "query_options": [
                                    "UDP_+_EDNS0_4096_D_K",
                                    "UDP_+_EDNS0_512_D_K"
                                ]
                            }
                        ],
                        "errors": [
                            {
                                "description": "No RRSIG covering the RRset was returned in the response.",
                                "code": "MISSING_RRSIG",
                                "servers": [
                                    "223.5.5.5"
                                ],
                                "query_options": [
                                    "UDP_+_EDNS0_4096_D_K",
                                    "UDP_+_EDNS0_512_D_K"
                                ]
                            }
                        ]
                    }
                ]
            }
        },
        "delegation": {
            "status": "BOGUS",
            "errors": [
                {
                    "description": "No valid RRSIGs made by a key corresponding to a DS RR were found covering the DNSKEY RRset, resulting in no secure entry point (SEP) into the zone.",
                    "code": "NO_SEP",
                    "servers": [
                        "223.5.5.5"
                    ],
                    "query_options": [
                        "UDP_+_EDNS0_4096_D_K",
                        "UDP_+_EDNS0_512_D_K"
                    ]
                },
                {
                    "description": "The DS RRset for the zone included algorithm 8 (RSASHA256), but no DS RR matched a DNSKEY with algorithm 8 that signs the zone's DNSKEY RRset.",
                    "code": "MISSING_SEP_FOR_ALG",
                    "servers": [
                        "223.5.5.5"
                    ],
                    "query_options": [
                        "UDP_+_EDNS0_4096_D_K",
                        "UDP_+_EDNS0_512_D_K"
                    ]
                }
            ]
        }
    },
    "5i8xkqjmqubv.top.": {
        "queries": {
            "5i8xkqjmqubv.top./IN/A": {
                "answer": [
                    {
                        "id": "5i8xkqjmqubv.top./IN/A",
                        "warnings": [
                            {
                                "description": "The server responded with no OPT record, rather than with RCODE FORMERR.",
                                "code": "EDNS_IGNORED",
                                "servers": [
                                    "223.5.5.5"
                                ],
                                "query_options": [
                                    "UDP_+_EDNS0_4096_D_K"
                                ]
                            }
                        ]
                    }
                ]
            },
            "5i8xkqjmqubv.top./IN/NS": {
                "answer": [
                    {
                        "id": "5i8xkqjmqubv.top./IN/NS",
                        "warnings": [
                            {
                                "description": "The server responded with no OPT record, rather than with RCODE FORMERR.",
                                "code": "EDNS_IGNORED",
                                "servers": [
                                    "223.5.5.5"
                                ],
                                "query_options": [
                                    "UDP_+_EDNS0_4096_D_K"
                                ]
                            }
                        ]
                    }
                ]
            },
            "5i8xkqjmqubv.top./IN/CNAME": {
                "nodata": [
                    {
                        "id": "5i8xkqjmqubv.top./IN/CNAME",
                        "warnings": [
                            {
                                "description": "The server responded with no OPT record, rather than with RCODE FORMERR.",
                                "code": "EDNS_IGNORED",
                                "servers": [
                                    "223.5.5.5"
                                ],
                                "query_options": [
                                    "UDP_+_EDNS0_4096_D_K"
                                ]
                            }
                        ]
                    }
                ]
            },
            "5i8xkqjmqubv.top./IN/SOA": {
                "answer": [
                    {
                        "id": "5i8xkqjmqubv.top./IN/SOA",
                        "warnings": [
                            {
                                "description": "The server responded with no OPT record, rather than with RCODE FORMERR.",
                                "code": "EDNS_IGNORED",
                                "servers": [
                                    "223.5.5.5"
                                ],
                                "query_options": [
                                    "TCP_+_EDNS0_4096_D",
                                    "UDP_+_EDNS0_4096_D_K",
                                    "UDP_+_EDNS0_4096_D_K_0x20"
                                ]
                            }
                        ]
                    }
                ]
            },
            "5i8xkqjmqubv.top./IN/MX": {
                "nodata": [
                    {
                        "id": "5i8xkqjmqubv.top./IN/MX",
                        "warnings": [
                            {
                                "description": "The server responded with no OPT record, rather than with RCODE FORMERR.",
                                "code": "EDNS_IGNORED",
                                "servers": [
                                    "223.5.5.5"
                                ],
                                "query_options": [
                                    "UDP_+_EDNS0_4096_D_K",
                                    "UDP_+_EDNS0_512_D_K"
                                ]
                            }
                        ]
                    }
                ]
            },
            "5i8xkqjmqubv.top./IN/TXT": {
                "nodata": [
                    {
                        "id": "5i8xkqjmqubv.top./IN/TXT",
                        "warnings": [
                            {
                                "description": "The server responded with no OPT record, rather than with RCODE FORMERR.",
                                "code": "EDNS_IGNORED",
                                "servers": [
                                    "223.5.5.5"
                                ],
                                "query_options": [
                                    "UDP_+_EDNS0_4096_D_K"
                                ]
                            }
                        ]
                    }
                ]
            },
            "5i8xkqjmqubv.top./IN/AAAA": {
                "nodata": [
                    {
                        "id": "5i8xkqjmqubv.top./IN/AAAA",
                        "warnings": [
                            {
                                "description": "The server responded with no OPT record, rather than with RCODE FORMERR.",
                                "code": "EDNS_IGNORED",
                                "servers": [
                                    "223.5.5.5"
                                ],
                                "query_options": [
                                    "UDP_+_EDNS0_4096_D_K"
                                ]
                            }
                        ]
                    }
                ]
            },
            "5i8xkqjmqubv.top./IN/DS": {
                "nodata": [
                    {
                        "id": "5i8xkqjmqubv.top./IN/DS",
                        "soa": [
                            {
                                "id": "top./IN/SOA",
                                "errors": [
                                    {
                                        "description": "No RRSIG covering the RRset was returned in the response.",
                                        "code": "MISSING_RRSIG",
                                        "servers": [
                                            "223.5.5.5"
                                        ],
                                        "query_options": [
                                            "UDP_+_EDNS0_4096_D_K"
                                        ]
                                    }
                                ]
                            }
                        ],
                        "warnings": [
                            {
                                "description": "The server responded with no OPT record, rather than with RCODE FORMERR.",
                                "code": "EDNS_IGNORED",
                                "servers": [
                                    "223.5.5.5"
                                ],
                                "query_options": [
                                    "UDP_+_EDNS0_4096_D_K"
                                ]
                            }
                        ],
                        "errors": [
                            {
                                "description": "No NSEC RR(s) were returned to validate the NODATA response.",
                                "code": "MISSING_NSEC_FOR_NODATA",
                                "servers": [
                                    "223.5.5.5"
                                ],
                                "query_options": [
                                    "UDP_+_EDNS0_4096_D_K"
                                ]
                            }
                        ]
                    }
                ]
            },
            "5i8xkqjmqubv.top./IN/DNSKEY": {
                "nodata": [
                    {
                        "id": "5i8xkqjmqubv.top./IN/DNSKEY",
                        "warnings": [
                            {
                                "description": "The server responded with no OPT record, rather than with RCODE FORMERR.",
                                "code": "EDNS_IGNORED",
                                "servers": [
                                    "223.5.5.5"
                                ],
                                "query_options": [
                                    "UDP_+_EDNS0_4096_D_K",
                                    "UDP_+_EDNS0_512_D_K"
                                ]
                            }
                        ]
                    }
                ]
            },
            "kc4dgy2f7e.5i8xkqjmqubv.top./IN/A": {
                "answer": [
                    {
                        "id": "kc4dgy2f7e.5i8xkqjmqubv.top./IN/A",
                        "warnings": [
                            {
                                "description": "The server responded with no OPT record, rather than with RCODE FORMERR.",
                                "code": "EDNS_IGNORED",
                                "servers": [
                                    "223.5.5.5"
                                ],
                                "query_options": [
                                    "UDP_+_EDNS0_4096_D_K"
                                ]
                            }
                        ]
                    }
                ]
            }
        },
        "delegation": {
            "status": "BOGUS"
        }
    }
}